MANIFEST.in
README.rst
setup.py
QiDataProcessing/BarHelper.py
QiDataProcessing/BarProvider.py
QiDataProcessing/BarProviderInfo.py
QiDataProcessing/BaseBarHelper.py
QiDataProcessing/QiDataController.py
QiDataProcessing/QiDataDirectory.py
QiDataProcessing/__init__.py
QiDataProcessing.egg-info/PKG-INFO
QiDataProcessing.egg-info/SOURCES.txt
QiDataProcessing.egg-info/dependency_links.txt
QiDataProcessing.egg-info/top_level.txt
QiDataProcessing/Config/Future.xml
QiDataProcessing/Config/HisFutures.xml
QiDataProcessing/Config/Holiday.xml
QiDataProcessing/Config/TradingFrame.xml
QiDataProcessing/Core/Bar.py
QiDataProcessing/Core/BarData.py
QiDataProcessing/Core/BinaryReader.py
QiDataProcessing/Core/CSharpUtils.py
QiDataProcessing/Core/DateTimeToOffsetMap.py
QiDataProcessing/Core/EnumBarType.py
QiDataProcessing/Core/EnumExchange.py
QiDataProcessing/Core/EnumFutureType.py
QiDataProcessing/Core/EnumLifePhase.py
QiDataProcessing/Core/EnumMarket.py
QiDataProcessing/Core/EnumRestoration.py
QiDataProcessing/Core/Exchange.py
QiDataProcessing/Core/FileHeader.py
QiDataProcessing/Core/FutureExchange.py
QiDataProcessing/Core/FutureProduct.py
QiDataProcessing/Core/Holiday.py
QiDataProcessing/Core/HolidayHelper.py
QiDataProcessing/Core/QiLogger.py
QiDataProcessing/Core/Quote.py
QiDataProcessing/Core/Tick.py
QiDataProcessing/Core/TradingDayHelper.py
QiDataProcessing/Core/__init__.py
QiDataProcessing/Core/TradingCalendar/2010.tc
QiDataProcessing/Core/TradingCalendar/2011.tc
QiDataProcessing/Core/TradingCalendar/2012.tc
QiDataProcessing/Core/TradingCalendar/2013.tc
QiDataProcessing/Core/TradingCalendar/2014.tc
QiDataProcessing/Core/TradingCalendar/2015.tc
QiDataProcessing/Core/TradingCalendar/2016.tc
QiDataProcessing/Core/TradingCalendar/2017.tc
QiDataProcessing/Core/TradingCalendar/2018.tc
QiDataProcessing/Core/TradingCalendar/2019.tc
QiDataProcessing/Core/TradingCalendar/2020.tc
QiDataProcessing/Core/TradingCalendar/2021.tc
QiDataProcessing/Core/TradingCalendar/2022.tc
QiDataProcessing/Core/TradingCalendar/2023.tc
QiDataProcessing/Core/TradingCalendar/2024.tc
QiDataProcessing/Instrument/Future.py
QiDataProcessing/Instrument/FutureManager.py
