Metadata-Version: 1.1
Name: QiDataProcessing
Version: 2.0.11
Summary: read data from custom bytes file
Home-page: https://github.com/CarlSnow/QiDataProcessing
Author: CarlSnow
Author-email: carl.snow.china@gmail.com
License: BSD License
Platform: all
Classifier: Development Status :: 4 - Beta
Classifier: Operating System :: OS Independent
Classifier: Intended Audience :: Developers
Classifier: License :: OSI Approved :: BSD License
Classifier: Programming Language :: Python
Classifier: Programming Language :: Python :: Implementation
Classifier: Programming Language :: Python :: 3.4
Classifier: Programming Language :: Python :: 3.5
Classifier: Programming Language :: Python :: 3.6
Classifier: Topic :: Software Development :: Libraries
